gobin/__init__.py
gobin/__main__.py
gobin/call_function.py
gobin/cli.py
gobin/config.py
gobin/main.py
gobin/tests.py
gobin/functions/__init__.py
gobin/functions/create_directory.py
gobin/functions/get_file_content.py
gobin/functions/get_files_info.py
gobin/functions/run_python.py
gobin/functions/run_shell.py
gobin/functions/write_file.py
gobin_cli-0.0.post15.dist-info/licenses/LICENSE
gobin_cli-0.0.post15.dist-info/METADATA
gobin_cli-0.0.post15.dist-info/WHEEL
gobin_cli-0.0.post15.dist-info/entry_points.txt
gobin_cli-0.0.post15.dist-info/top_level.txt
gobin_cli-0.0.post15.dist-info/RECORD
