Metadata-Version: 2.4
Name: gobin-cli
Version: 0.0.post15
Summary: AI Coding Agent CLI
Author: Xgramm Platforms
License: MIT
Keywords: ai,cli,developer-tools,automation
Classifier: Development Status :: 3 - Alpha
Classifier: Intended Audience :: Developers
Classifier: License :: OSI Approved :: MIT License
Classifier: Programming Language :: Python :: 3
Classifier: Programming Language :: Python :: 3.9
Classifier: Programming Language :: Python :: 3.10
Classifier: Programming Language :: Python :: 3.11
Classifier: Programming Language :: Python :: 3.12
Classifier: Topic :: Software Development :: Libraries :: Application Frameworks
Classifier: Topic :: Utilities
Requires-Python: >=3.8
License-File: LICENSE
Requires-Dist: python-dotenv>=1.0.0
Requires-Dist: rich>=13.0.0
Requires-Dist: prompt_toolkit>=3.0.0
Requires-Dist: google-genai>=0.3.0
Dynamic: license-file
